Workbook

Sheet README
A1: SFDF — Strategic Financing Decision Framework
A2: Excel Scorer v1.0 — Bootstrap vs. Equity Decision Tool
A5: How to use this scorer
A7: Step 1 | B7: Open the 'Scorer' tab. You will see 15 factors organised in 4 dimensions.
A8: Step 2 | B8: For each factor, enter a score from 1 to 5 in the BLUE column. Anchor descriptions are shown next to each scale.
A9: Step 3 | B9: The Net Score and Recommendation Zone update automatically at the top of the Scorer tab.
A10: Step 4 | B10: Open the 'Brief' tab to see your one-page Decision Brief, including top drivers, watch-outs, and suggested next actions.
A11: Step 5 | B11: Open the 'Cases' tab to see three pre-loaded worked examples (Bootstrapped SaaS, Capital-intensive Deep-tech, Ambiguous Marketplace) for calibration.
A13: Reading the output
A15: Net Score range | B15: −2.0 (Strong Bootstrap) to +2.0 (Strong Equity)
A16: Strong Bootstrap | B16: Net Score ≤ −1.0
A17: Bootstrap-leaning | B17: −1.0 < Net Score ≤ −0.2
A18: Ambiguous | B18: −0.2 < Net Score < +0.2 (genuine ambiguity — model both paths)
A19: Equity-leaning | B19: +0.2 ≤ Net Score < +1.0
A20: Strong Equity | B20: Net Score ≥ +1.0
A22: Important caveats
A24: • | B24: The SFDF is a directional decision-support tool, NOT a prescriptive algorithm.
A25: • | B25: The output is a recommended ZONE, not a verdict. Reason through the watch-outs.
A26: • | B26: Final decisions should be made with an advisor, not from the score alone.
A27: • | B27: Weights are derived from the SLR and may be revised based on validation feedback.
A29: Theoretical anchors
A31: Agency Theory | B31: Jensen & Meckling (1976) — control / dilution tensions when raising equity
A32: Resource Dependence | B32: Pfeffer & Salancik (1978) — why founders rationally accept dilution for resource access
A33: Founder choice | B33: Wasserman (2017) — risk tolerance, control preference, growth ambition
A34: VC contracting | B34: Kaplan & Strömberg (2003) — empirical anchors for venture and market factors
A35: VC value-add | B35: Hellmann & Puri (2002) — beyond capital: networks, hires, governance
A36: Bootstrapping | B36: Winborg & Landström (2001) — financial bootstrapping techniques
A37: DSR / FEDS | B37: Peffers et al. (2007); Venable et al. (2016) — methodology and evaluation

Sheet Scorer
A1: SFDF Scorer — Enter your scores in the BLUE column (D)
A3: Net Score: | B3: =Calc!B22 -> 0
A4: Recommendation Zone: | B4: =IF(B3<=-1,"STRONG BOOTSTRAP",IF(B3<=-0.2,"Bootstrap-leaning",IF(B3<0.2,"AMBIGUOUS — model both",IF(B3<1,"Equity-leaning","STRONG EQUITY")))) -> AMBIGUOUS — model both
A5: Total factors scored: | B5: =COUNT(D11:D14,D17:D20,D23:D25,D28:D31) -> 0 | C5: / 15 (score every factor for a valid result)
A9: # | B9: Factor | C9: Direction | D9: Your Score (1–5) | E9: Anchor (1) | F9: Anchor (5) | G9: Citation
A10: DIMENSION A — Founder & Team (weight 0.25)
A11: A1 | B11: Risk tolerance | C11: Higher → B | E11: Very low | F11: Very high | G11: Wasserman (2017)
A12: A2 | B12: Control preference | C12: Higher → B | E12: Growth-first | F12: Autonomy-first | G12: Wasserman (2017)
A13: A3 | B13: Domain experience | C13: Higher → B | E13: First-time founder | F13: Multiple prior exits | G13: Kaplan & Strömberg (2003)
A14: A4 | B14: Personal runway | C14: Higher → B | E14: <3 months | F14: 24+ months | G14: Bhidé (2000)
A16: DIMENSION B — Venture (weight 0.30)
A17: B1 | B17: Capital intensity | C17: Higher → E | E17: Very low | F17: Very high | G17: Kaplan & Strömberg (2003)
A18: B2 | B18: Time-to-revenue | C18: Higher → E | E18: <3 months | F18: 24+ months | G18: Hellmann & Puri (2002)
A19: B3 | B19: Existing traction | C19: Higher → B | E19: Idea only | F19: Scaling revenue | G19: Kaplan & Strömberg (2003)
A20: B4 | B20: Defensibility / IP | C20: Higher → E | E20: No moat | F20: Strong moat | G20: Hellmann & Puri (2002)
A22: DIMENSION C — Market (weight 0.20)
A23: C1 | B23: Market timing pressure | C23: Higher → E | E23: Patient market | F23: Winner-takes-most | G23: Hellmann & Puri (2002)
A24: C2 | B24: Competitive density | C24: Higher → E | E24: Greenfield | F24: Heavily contested | G24: Kaplan & Strömberg (2003)
A25: C3 | B25: Customer acquisition cost | C25: Higher → E | E25: Organic / low CAC | F25: Paid / high CAC | G25: SLR synthesis
A27: DIMENSION D — Strategic (weight 0.25)
A28: D1 | B28: Exit horizon | C28: Higher → E | E28: Long / no exit | F28: Fast exit (3–5 yrs) | G28: Wasserman (2017)
A29: D2 | B29: Growth ambition | C29: Higher → E | E29: Lifestyle | F29: Hypergrowth | G29: Wasserman (2017)
A30: D3 | B30: Need for VC value-add | C30: Higher → E | E30: Capital not needed | F30: Critical for hires/network | G30: Hellmann & Puri (2002)
A31: D4 | B31: Optionality preference | C31: Higher → B | E31: Commit to one path | F31: Preserve future options | G31: Winborg & Landström (2001)
A33: Tip: a score of 3 is neutral and contributes nothing. Scores of 1 and 5 contribute the most.

Sheet Calc
A1: SFDF Calculation — Do not edit
A2: Factor | B2: Score | C2: Centered (Score-3) | D2: Direction | E2: Dimension | F2: Contribution | H2: Aligned (× sign of net)
A3: A1 | B3: =IF(ISNUMBER(Scorer!D11),Scorer!D11,3) -> 3 | C3: =B3-3 -> 0 | D3: B | E3: A | F3: =IF(D3="E",C3,-C3) -> 0 | H3: =F3*SIGN($B$22) -> 0
A4: A2 | B4: =IF(ISNUMBER(Scorer!D12),Scorer!D12,3) -> 3 | C4: =B4-3 -> 0 | D4: B | E4: A | F4: =IF(D4="E",C4,-C4) -> 0 | H4: =F4*SIGN($B$22) -> 0
A5: A3 | B5: =IF(ISNUMBER(Scorer!D13),Scorer!D13,3) -> 3 | C5: =B5-3 -> 0 | D5: B | E5: A | F5: =IF(D5="E",C5,-C5) -> 0 | H5: =F5*SIGN($B$22) -> 0
A6: A4 | B6: =IF(ISNUMBER(Scorer!D14),Scorer!D14,3) -> 3 | C6: =B6-3 -> 0 | D6: B | E6: A | F6: =IF(D6="E",C6,-C6) -> 0 | H6: =F6*SIGN($B$22) -> 0
A7: B1 | B7: =IF(ISNUMBER(Scorer!D17),Scorer!D17,3) -> 3 | C7: =B7-3 -> 0 | D7: E | E7: B | F7: =IF(D7="E",C7,-C7) -> 0 | H7: =F7*SIGN($B$22) -> 0
A8: B2 | B8: =IF(ISNUMBER(Scorer!D18),Scorer!D18,3) -> 3 | C8: =B8-3 -> 0 | D8: E | E8: B | F8: =IF(D8="E",C8,-C8) -> 0 | H8: =F8*SIGN($B$22) -> 0
A9: B3 | B9: =IF(ISNUMBER(Scorer!D19),Scorer!D19,3) -> 3 | C9: =B9-3 -> 0 | D9: B | E9: B | F9: =IF(D9="E",C9,-C9) -> 0 | H9: =F9*SIGN($B$22) -> 0
A10: B4 | B10: =IF(ISNUMBER(Scorer!D20),Scorer!D20,3) -> 3 | C10: =B10-3 -> 0 | D10: E | E10: B | F10: =IF(D10="E",C10,-C10) -> 0 | H10: =F10*SIGN($B$22) -> 0
A11: C1 | B11: =IF(ISNUMBER(Scorer!D23),Scorer!D23,3) -> 3 | C11: =B11-3 -> 0 | D11: E | E11: C | F11: =IF(D11="E",C11,-C11) -> 0 | H11: =F11*SIGN($B$22) -> 0
A12: C2 | B12: =IF(ISNUMBER(Scorer!D24),Scorer!D24,3) -> 3 | C12: =B12-3 -> 0 | D12: E | E12: C | F12: =IF(D12="E",C12,-C12) -> 0 | H12: =F12*SIGN($B$22) -> 0
A13: C3 | B13: =IF(ISNUMBER(Scorer!D25),Scorer!D25,3) -> 3 | C13: =B13-3 -> 0 | D13: E | E13: C | F13: =IF(D13="E",C13,-C13) -> 0 | H13: =F13*SIGN($B$22) -> 0
A14: D1 | B14: =IF(ISNUMBER(Scorer!D28),Scorer!D28,3) -> 3 | C14: =B14-3 -> 0 | D14: E | E14: D | F14: =IF(D14="E",C14,-C14) -> 0 | H14: =F14*SIGN($B$22) -> 0
A15: D2 | B15: =IF(ISNUMBER(Scorer!D29),Scorer!D29,3) -> 3 | C15: =B15-3 -> 0 | D15: E | E15: D | F15: =IF(D15="E",C15,-C15) -> 0 | H15: =F15*SIGN($B$22) -> 0
A16: D3 | B16: =IF(ISNUMBER(Scorer!D30),Scorer!D30,3) -> 3 | C16: =B16-3 -> 0 | D16: E | E16: D | F16: =IF(D16="E",C16,-C16) -> 0 | H16: =F16*SIGN($B$22) -> 0
A17: D4 | B17: =IF(ISNUMBER(Scorer!D31),Scorer!D31,3) -> 3 | C17: =B17-3 -> 0 | D17: B | E17: D | F17: =IF(D17="E",C17,-C17) -> 0 | H17: =F17*SIGN($B$22) -> 0
A19: Dim A avg contribution: | B19: =AVERAGE(F3:F6) -> 0
A20: Dim B avg contribution: | B20: =AVERAGE(F7:F10) -> 0
A21: Dim C avg contribution: | B21: =AVERAGE(F11:F13) -> 0
A22: NET SCORE: | B22: =B19*B26 + B20*B27 + B21*B28 + B23*B29 -> 0
A23: Dim D avg contribution: | B23: =AVERAGE(F14:F17) -> 0
A25: Weights:
A26: Dim A | B26: 0.25
A27: Dim B | B27: 0.3
A28: Dim C | B28: 0.2
A29: Dim D | B29: 0.25
A32: Top 3 Drivers:
A33: =INDEX($A$3:$A$17,MATCH(LARGE($H$3:$H$17,1),$H$3:$H$17,0)) -> A1 | B33: =LARGE($H$3:$H$17,1) -> 0
A34: =INDEX($A$3:$A$17,MATCH(LARGE($H$3:$H$17,2),$H$3:$H$17,0)) -> A1 | B34: =LARGE($H$3:$H$17,2) -> 0
A35: =INDEX($A$3:$A$17,MATCH(LARGE($H$3:$H$17,3),$H$3:$H$17,0)) -> A1 | B35: =LARGE($H$3:$H$17,3) -> 0
A37: Top 2 Watch-outs:
A38: =INDEX($A$3:$A$17,MATCH(SMALL($H$3:$H$17,1),$H$3:$H$17,0)) -> A1 | B38: =SMALL($H$3:$H$17,1) -> 0
A39: =INDEX($A$3:$A$17,MATCH(SMALL($H$3:$H$17,2),$H$3:$H$17,0)) -> A1 | B39: =SMALL($H$3:$H$17,2) -> 0

Sheet Brief
A1: DECISION BRIEF
A2: Generated by the Strategic Financing Decision Framework (SFDF v1.0)
A4: Recommendation Zone
A5: =Scorer!B4 -> AMBIGUOUS — model both
A7: Net Score | B7: =Scorer!B3 -> 0 | C7: Range | D7: −2.0 (Strong Bootstrap) ↔ +2.0 (Strong Equity)
A9: TOP 3 DRIVERS
A10: These three factors are pulling your decision most strongly toward the recommended zone.
A11: Rank | B11: Factor ID | C11: Contribution
A12: 1 | B12: =Calc!A33 -> A1 | C12: =Calc!B33 -> 0
A13: 2 | B13: =Calc!A34 -> A1 | C13: =Calc!B34 -> 0
A14: 3 | B14: =Calc!A35 -> A1 | C14: =Calc!B35 -> 0
A16: TOP 2 WATCH-OUTS
A17: These factors are most in tension with the recommendation. They are the strongest reasons to reconsider.
A18: Rank | B18: Factor ID | C18: Contribution (negative = opposing)
A19: 1 | B19: =Calc!A38 -> A1 | C19: =Calc!B38 -> 0
A20: 2 | B20: =Calc!A39 -> A1 | C20: =Calc!B39 -> 0
A23: SUGGESTED NEXT ACTIONS
A25: =IF(Scorer!B3<=-1,"1. Map revenue-financing instruments (customer pre-payments, factoring, revenue-based financing) — Winborg & Landström (2001).",IF(Scorer!B3<=-0.2,"1. Set explicit traction milestones (MRR, retention) that would justify a future raise at higher valuation.",IF(Scorer!B3<0.2,"1. Build two financial scenarios — bootstrapped path and seed-funded path — for the next 18 months and compare them.",IF(Scorer!B3<1,"1. Identify 8–10 target investors aligned with your stage and sector. Begin relationships before formally raising.","1. Begin preparing the seed/Series-A round formally. Capital intensity, market timing, or competitive density makes raising unavoidable.")))) -> 1. Build two financial scenarios — bootstrapped path and seed-funded path — for the next 18 months and compare them.
A26: =IF(Scorer!B3<=-1,"2. Apply for non-dilutive funding: national grants (IAPMEI, Portugal 2030), EIC Accelerator, Horizon Europe.",IF(Scorer!B3<=-0.2,"2. Apply for non-dilutive grants in parallel — they extend runway without dilution.",IF(Scorer!B3<0.2,"2. Identify the 2–3 factors that would tip your decision (e.g., a pivot in market timing, a new entrant). Track them.",IF(Scorer!B3<1,"2. Stage the raise: pre-seed first to hit a milestone, seed after, rather than raising one large round.","2. Prioritise investor fit using Hellmann & Puri (2002) value-add criteria — networks, hires, governance — not just term-sheet economics.")))) -> 2. Identify the 2–3 factors that would tip your decision (e.g., a pivot in market timing, a new entrant). Track them.
A27: =IF(Scorer!B3<=-1,"3. Resist the temptation to raise out of FOMO. Re-run the SFDF every 6 months as the venture evolves.",IF(Scorer!B3<=-0.2,"3. Begin informal investor relationships now, but do not pitch. Build the relationship before the raise.",IF(Scorer!B3<0.2,"3. Speak with at least one founder who took each path before deciding.",IF(Scorer!B3<1,"3. Speak with portfolio founders of your target investors — assess their actual value-add post-investment.","3. Negotiate governance terms carefully: board composition, protective provisions, vesting. Cite Kaplan & Strömberg (2003) for benchmarks.")))) -> 3. Speak with at least one founder who took each path before deciding.
A28: =IF(Scorer!B3<=-1,"4. If watch-outs surface (e.g., a competitor raises a large round), re-evaluate.",IF(Scorer!B3<=-0.2,"4. Use this period to strengthen the founder team and reduce A3 (domain experience) risk if applicable.",IF(Scorer!B3<0.2,"4. Consider revenue-based financing or a small angel round as a middle path.",IF(Scorer!B3<1,"4. Set explicit dilution targets for each round (e.g., max 20% per round) before negotiation.","4. Plan for the next round at fundraising time: founders who raise must already model how Series A will look.")))) -> 4. Consider revenue-based financing or a small angel round as a middle path.
A30: The SFDF is a directional decision-support tool, not a prescriptive algorithm. Final decisions belong with the founder and their advisors.

Sheet Cases
A1: Worked Cases — Calibration & Reference
A2: Reference scores for the three calibration cases. To run a case, copy the scores into the Scorer tab manually.
A4: Factor | B4: Case 1: Bootstrapped SaaS | C4: Case 2: Capital-Intensive Deep-Tech | D4: Case 3: Ambiguous Marketplace
A5: A1 Risk tolerance | B5: 4 | C5: 3 | D5: 4
A6: A2 Control preference | B6: 5 | C6: 2 | D6: 2
A7: A3 Domain experience | B7: 4 | C7: 4 | D7: 1
A8: A4 Personal runway | B8: 3 | C8: 1 | D8: 3
A9: B1 Capital intensity | B9: 1 | C9: 5 | D9: 2
A10: B2 Time-to-revenue | B10: 1 | C10: 5 | D10: 3
A11: B3 Existing traction | B11: 4 | C11: 1 | D11: 2
A12: B4 Defensibility / IP | B12: 2 | C12: 5 | D12: 2
A13: C1 Market timing | B13: 1 | C13: 5 | D13: 5
A14: C2 Competitive density | B14: 2 | C14: 5 | D14: 4
A15: C3 CAC trajectory | B15: 2 | C15: 3 | D15: 5
A16: D1 Exit horizon | B16: 2 | C16: 4 | D16: 5
... A19: D4 Optionality preference | B19: 5 | C19: 1 | D19: 3
A21: Expected Net Score: | B21: ≈ −1.22 | C21: ≈ +1.43 | D21: ≈ +0.70
A22: Expected Zone: | B22: Strong Bootstrap | C22: Strong Equity | D22: Equity-leaning
